pyHarm/Analysis/ABCAnalysis.py
pyHarm/Analysis/FRF_NonLinear.py
pyHarm/Analysis/FactoryNonLinearStudy.py
pyHarm/Analysis/Linear_Analysis.py
pyHarm/Analysis/README.md
pyHarm/Analysis/__init__.py
pyHarm/BaseUtilFuncs.py
pyHarm/CoordinateSystem.py
pyHarm/Correctors/ABCCorrector.py
pyHarm/Correctors/CorrectorArcLength.py
pyHarm/Correctors/CorrectorNoContinuation.py
pyHarm/Correctors/CorrectorPseudoArcLength.py
pyHarm/Correctors/FactoryCorrector.py
pyHarm/Correctors/README.md
pyHarm/Correctors/__init__.py
pyHarm/DofGrabber.py
pyHarm/DynamicOperator.py
pyHarm/Elements/ABCElement.py
pyHarm/Elements/FactoryElements.py
pyHarm/Elements/NodeToNodeElements/CosinusForcing.py
pyHarm/Elements/NodeToNodeElements/CubicSpring.py
pyHarm/Elements/NodeToNodeElements/DLFTElements/DLFT3D.py
pyHarm/Elements/NodeToNodeElements/DLFTElements/DLFTElement.py
pyHarm/Elements/NodeToNodeElements/DLFTElements/DLFTFriction.py
pyHarm/Elements/NodeToNodeElements/DLFTElements/DLFTUniGap.py
pyHarm/Elements/NodeToNodeElements/DLFTElements/README.md
pyHarm/Elements/NodeToNodeElements/DLFTElements/__init__.py
pyHarm/Elements/NodeToNodeElements/GeneralOrderElement.py
pyHarm/Elements/NodeToNodeElements/GeneralOrderForcing.py
pyHarm/Elements/NodeToNodeElements/Jenkins.py
pyHarm/Elements/NodeToNodeElements/LinearDamper.py
pyHarm/Elements/NodeToNodeElements/LinearSpring.py
pyHarm/Elements/NodeToNodeElements/NodeToNodeElement.py
pyHarm/Elements/NodeToNodeElements/Penalty3D.py
pyHarm/Elements/NodeToNodeElements/PenaltyBilateralGap.py
pyHarm/Elements/NodeToNodeElements/PenaltyUnilateralGap.py
pyHarm/Elements/NodeToNodeElements/README.md
pyHarm/Elements/NodeToNodeElements/SinusForcing.py
pyHarm/Elements/NodeToNodeElements/WRElements/README.md
pyHarm/Elements/NodeToNodeElements/WRElements/__init__.py
pyHarm/Elements/NodeToNodeElements/__init__.py
pyHarm/Elements/README.md
pyHarm/Elements/SubstructureMatrixElements/GeneralOrderMatrixElement.py
pyHarm/Elements/SubstructureMatrixElements/LinearHystMatrixElement.py
pyharm_os-1.1.3.dist-info/LICENSE
pyharm_os-1.1.3.dist-info/METADATA
pyharm_os-1.1.3.dist-info/WHEEL
pyharm_os-1.1.3.dist-info/entry_points.txt
pyharm_os-1.1.3.dist-info/RECORD
