Metadata-Version: 2.3
Name: pyHarm-os
Version: 1.1.3
Summary: A Harmonic Balance code for mechanical vibration systems with nonlinearities.
License: Apache-2.0
Author: Owner pyHarm
Author-email: pyharm.fr.saf@safrangroup.com
Requires-Python: >=3.11
Classifier: License :: OSI Approved :: Apache Software License
Classifier: Programming Language :: Python :: 3
Classifier: Programming Language :: Python :: 3.11
Classifier: Programming Language :: Python :: 3.12
Classifier: Programming Language :: Python :: 3.13
Requires-Dist: click (>=8.1.8,<9.0.0)
Requires-Dist: h5py (>=3.13.0,<4.0.0)
Requires-Dist: jax (>=0.5.1,<0.6.0)
Requires-Dist: matplotlib (>=3.10.1,<4.0.0)
Requires-Dist: nbformat (>=5.10.4,<6.0.0)
Requires-Dist: notebook (>=7.3.2,<8.0.0)
Requires-Dist: numba (>=0.61.0,<0.62.0)
Requires-Dist: numpy (<2.2)
Requires-Dist: pandas (>=2.2.3,<3.0.0)
Requires-Dist: pydantic (>=2.10.6,<3.0.0)
Requires-Dist: scipy (>=1.15.2,<2.0.0)
Project-URL: Repository, https://gitlab.com/drti/pyharm
